{
  "title": "Qwartz",
  "customer": "Qwartz",
  "date": 2012,
  "tags": ["logo", "design"],
  "description": "Le fondateur des Qwartz Music Awards a un projet de distribution de musique en ligne, le Qwartz Music Store. Il me demande un logo. La com des Awards changeant chaque année sans grande cohérence, je lui propose de mettre en place un seul logo qui se décline pour les deux activités. Il accepte. Le Music Store déposera le bilan à l'état de projet. Ma dernière facture ne sera pas acquittée."
}
